{
	"v1bP6olgtx0": {
		"image": "v1bP6olgtx0",
		"name": "Joe Reed",
		"link": "https://unsplash.com/@joerobot",
		"url": "https://images.unsplash.com/photo-1460378150801-e2c95cb65a50?ixlib=rb-0.3.5&q=80&fm=jpg&crop=entropy&cs=tinysrgb&w=1600&h=900&rect=&fit=crop&s=ac0d2311edf659059eed662ae6b76896"
	},
	"V6s1cmE39XM": {
		"image": "V6s1cmE39XM",
		"name": "Patrick Fore",
		"link": "https://unsplash.com/@patrickian4",
		"url": "https://images.unsplash.com/photo-1451417379553-15d8e8f49cde?ixlib=rb-0.3.5&q=80&fm=jpg&crop=entropy&cs=tinysrgb&w=1600&h=900&rect=&fit=crop&s=5ba60e74152b75a8c79a626a4589890b"
	},
	"5Kt4DKFUiQk": {
		"image": "5Kt4DKFUiQk",
		"name": "Anton Darius | Sollers",
		"link": "https://unsplash.com/@thesollers",
		"url": "https://images.unsplash.com/photo-1464062901860-6bfe29568e56?ixlib=rb-0.3.5&q=80&fm=jpg&crop=entropy&cs=tinysrgb&w=1600&h=900&rect=&fit=crop&s=ea56095647e0a4bff59757d770cee62f"
	},
	"q1wd1Q2LYHc": {
		"image": "q1wd1Q2LYHc",
		"name": "Jakub Kriz",
		"link": "https://unsplash.com/@jakubkriz",
		"url": "https://images.unsplash.com/photo-1469353680598-5dc830efef5c?ixlib=rb-0.3.5&q=80&fm=jpg&crop=entropy&cs=tinysrgb&w=1600&h=900&rect=&fit=crop&s=55320e81b0ce05035d0f99ba8e40e2d5"
	},
	"o-zOatT4kQw": {
		"image": "o-zOatT4kQw",
		"name": "Tyssul Patel",
		"link": "https://unsplash.com/@tyssulpatel",
		"url": "https://images.unsplash.com/38/L2NfDz5SOm7Gbf755qpw_DSCF0490.jpg?ixlib=rb-0.3.5&q=80&fm=jpg&crop=entropy&cs=tinysrgb&w=1600&h=900&rect=&fit=crop&s=166f060ef1c3cc84b76d4f1ff942a67e"
	},
	"le60j2br1BI": {
		"image": "le60j2br1BI",
		"name": "Zachary Staines",
		"link": "https://unsplash.com/@antibodies",
		"url": "https://images.unsplash.com/photo-1454540723233-f0b9ff08b132?ixlib=rb-0.3.5&q=80&fm=jpg&crop=entropy&cs=tinysrgb&w=1600&h=900&rect=&fit=crop&s=6fbdf2b7d854dd7176377f4f6b32a18e"
	},
	"NehgTfCRJqg": {
		"image": "NehgTfCRJqg",
		"name": "Tom Mussak",
		"link": "https://unsplash.com/@tom_mu",
		"url": "https://images.unsplash.com/photo-1465216762568-7ca555feddfe?ixlib=rb-0.3.5&q=80&fm=jpg&crop=entropy&cs=tinysrgb&w=1600&h=900&rect=&fit=crop&s=22373f43ece3e5326731f97ca02f5c6e"
	},
	"8-o4p16GzSc": {
		"image": "8-o4p16GzSc",
		"name": "FORREST CAVALE",
		"link": "https://unsplash.com/@forrestcavale",
		"url": "https://images.unsplash.com/photo-1420578481027-ed20272bbb81?ixlib=rb-0.3.5&q=80&fm=jpg&crop=entropy&cs=tinysrgb&w=1600&h=900&rect=&fit=crop&s=4270ee6591d61107b18efa1d37c2ad27"
	},
	"VzEgZgibC5Y": {
		"image": "VzEgZgibC5Y",
		"name": "Eric Welch",
		"link": "https://unsplash.com/@eric_welch",
		"url": "https://images.unsplash.com/photo-1493855344473-0378f32bd0d4?ixlib=rb-0.3.5&q=80&fm=jpg&crop=entropy&cs=tinysrgb&w=1600&h=900&rect=&fit=crop&s=f1330e9190c37a2844961b23865a86f8"
	},
	"r75qppvP-FE": {
		"image": "r75qppvP-FE",
		"name": "Eric Huang",
		"link": "https://unsplash.com/@erichuang78910",
		"url": "https://images.unsplash.com/photo-1442589031151-61d5645469d7?ixlib=rb-0.3.5&q=80&fm=jpg&crop=entropy&cs=tinysrgb&w=1600&h=900&rect=&fit=crop&s=3259827bb76c7f5e37f6bf6439f63c65"
	},
	"aAQwxN-EOUI": {
		"image": "aAQwxN-EOUI",
		"name": "Mark Asthoff",
		"link": "https://unsplash.com/@qa9de",
		"url": "https://images.unsplash.com/photo-1459197648846-52de5e4d1e9a?ixlib=rb-0.3.5&q=80&fm=jpg&crop=entropy&cs=tinysrgb&w=1600&h=900&rect=&fit=crop&s=a99d4d22a97b72ef260ccb95f5fbff3e"
	},
	"OZdKEwDXXJU": {
		"image": "OZdKEwDXXJU",
		"name": "Paul Gilmore",
		"link": "https://unsplash.com/@paulgilmore_",
		"url": "https://images.unsplash.com/photo-1465326117523-6450112b60b2?ixlib=rb-0.3.5&q=80&fm=jpg&crop=entropy&cs=tinysrgb&w=1600&h=900&rect=&fit=crop&s=4398e937bae891f3de08d61989fa7981"
	},
	"Di9ffX_Lb5Y": {
		"image": "Di9ffX_Lb5Y",
		"name": "Quino Al",
		"link": "https://unsplash.com/@quinoal",
		"url": "https://images.unsplash.com/photo-1466007599518-a696875f4757?ixlib=rb-0.3.5&q=80&fm=jpg&crop=entropy&cs=tinysrgb&w=1600&h=900&rect=&fit=crop&s=8156c6a2380c995975a5a03bf61eb269"
	}
}